unbiasedness/__init__.py
unbiasedness/bootstrap.py
unbiasedness/numba_jit.py
unbiasedness/table.py
unbiasedness/unbiasedness.py
unbiasedness/windows.py
unbiasedness-0.1.2.dist-info/LICENSE
unbiasedness-0.1.2.dist-info/METADATA
unbiasedness-0.1.2.dist-info/WHEEL
unbiasedness-0.1.2.dist-info/RECORD
