Metadata-Version: 2.1
Name: unbiasedness
Version: 0.1.2
Summary: Functions for estimating unbiasedness regressions.
License: Apache License, Version 2
Author: Vincent Grégoire
Author-email: vincent.gregoire@gmail.com
Requires-Python: >=3.10,<4.0
Classifier: License :: Other/Proprietary License
Classifier: Programming Language :: Python :: 3
Classifier: Programming Language :: Python :: 3.10
Classifier: Programming Language :: Python :: 3.11
Classifier: Programming Language :: Python :: 3.12
Requires-Dist: numba (>=0,<1)
Requires-Dist: numpy (>=1.24,<2.0)
Requires-Dist: pandas (>=2.0,<3.0)
Requires-Dist: statsmodels (>=0,<1)
